screenconnect/__init__.py
screenconnect/api.py
screenconnect/enumerations.py
screenconnect/error.py
screenconnect/events.py
screenconnect/session.py
screenconnect/session_group.py
tests/__init__.py
screenconnect-0.1.0.dist-info/LICENSE
screenconnect-0.1.0.dist-info/METADATA
screenconnect-0.1.0.dist-info/WHEEL
screenconnect-0.1.0.dist-info/top_level.txt
screenconnect-0.1.0.dist-info/RECORD
